{
  "builders": [
    {
      "name": "alpine35",
      "output_directory": "output/alpine35",
      "iso_url": "https://mirrors.edge.kernel.org/alpine/v3.5/releases/x86_64/alpine-virt-3.5.3-x86_64.iso",
      "iso_checksum": "sha256:580bc6379e4b246d24b5e32d2637319a60ac953279b3e0df523222ef561bf2f5",
      "boot_wait": "5s",
      "disk_size": 1,
      "headless": true,
      "shutdown_command": "poweroff",
      "ssh_password": "vagrant",
      "ssh_port": 22,
      "ssh_timeout": "10s",
      "ssh_username": "root",
      "type": "vmware-iso"
    },
    {
      "name": "alpine35-hyperv",
      "output_directory": "output/alpine35-hyperv",
      "iso_url": "https://mirrors.edge.kernel.org/alpine/v3.5/releases/x86_64/alpine-vanilla-3.5.3-x86_64.iso",
      "iso_checksum": "sha256:3cca39f256f6a11d89a1c89a54982e9806d3df0fd785dc66ff26d3c670c3d648",
      "boot_wait": "5s",
      "disk_size": 1,
      "headless": true,
      "shutdown_command": "poweroff",
      "ssh_password": "vagrant",
      "ssh_port": 22,
      "ssh_timeout": "10s",
      "ssh_username": "root",
      "type": "vmware-iso"
    },
    {
      "name": "alpine36",
      "output_directory": "output/alpine36",
      "iso_url": "https://mirrors.edge.kernel.org/alpine/v3.6/releases/x86_64/alpine-virt-3.6.5-x86_64.iso",
      "iso_checksum": "sha256:b5936e27487e605ea3cbf040d444505ea7fd735021258d7b119faaa9b4b5b083",
      "boot_wait": "5s",
      "disk_size": 1,
      "headless": true,
      "shutdown_command": "poweroff",
      "ssh_password": "vagrant",
      "ssh_port": 22,
      "ssh_timeout": "10s",
      "ssh_username": "root",
      "type": "vmware-iso"
    },
    {
      "name": "alpine37",
      "output_directory": "output/alpine37",
      "iso_url": "https://mirrors.edge.kernel.org/alpine/v3.7/releases/x86_64/alpine-virt-3.7.3-x86_64.iso",
      "iso_checksum": "sha256:2f7a23fc31a6f67348e5614597b23ab8d9340e8a0f4368e96797b1a6c65fa6b8",
      "boot_wait": "5s",
      "disk_size": 1,
      "headless": true,
      "shutdown_command": "poweroff",
      "ssh_password": "vagrant",
      "ssh_port": 22,
      "ssh_timeout": "10s",
      "ssh_username": "root",
      "type": "vmware-iso"
    },
    {
      "name": "alpine38",
      "output_directory": "output/alpine38",
      "iso_url": "https://mirrors.edge.kernel.org/alpine/v3.8/releases/x86_64/alpine-virt-3.8.5-x86_64.iso",
      "iso_checksum": "sha256:9c1d8222c6af31f5e1e62dc25b5f4f922a27a6b3c7f8e136febd0c66dcdb51e3",
      "boot_wait": "5s",
      "disk_size": 1,
      "headless": true,
      "shutdown_command": "poweroff",
      "ssh_password": "vagrant",
      "ssh_port": 22,
      "ssh_timeout": "10s",
      "ssh_username": "root",
      "type": "vmware-iso"
    },
    {
      "name": "alpine39",
      "output_directory": "output/alpine39",
      "iso_url": "https://mirrors.edge.kernel.org/alpine/v3.9/releases/x86_64/alpine-virt-3.9.6-x86_64.iso",
      "iso_checksum": "sha256:888d2245ec900351d3613d831838d1459ac29635b56bd528cd50fd643200d4cf",
      "boot_wait": "5s",
      "disk_size": 1,
      "headless": true,
      "shutdown_command": "poweroff",
      "ssh_password": "vagrant",
      "ssh_port": 22,
      "ssh_timeout": "10s",
      "ssh_username": "root",
      "type": "vmware-iso"
    },
    {
      "name": "alpine310",
      "output_directory": "output/alpine310",
      "iso_url": "https://mirrors.edge.kernel.org/alpine/v3.10/releases/x86_64/alpine-virt-3.10.9-x86_64.iso",
      "iso_checksum": "sha256:f4e6973b61f37c445bafd99f3beecabc9a68a56b17014297b1505d35faae85fb",
      "boot_wait": "5s",
      "disk_size": 1,
      "headless": true,
      "shutdown_command": "poweroff",
      "ssh_password": "vagrant",
      "ssh_port": 22,
      "ssh_timeout": "10s",
      "ssh_username": "root",
      "type": "vmware-iso"
    },
    {
      "name": "alpine311",
      "output_directory": "output/alpine311",
      "iso_url": "https://mirrors.edge.kernel.org/alpine/v3.11/releases/x86_64/alpine-virt-3.11.13-x86_64.iso",
      "iso_checksum": "sha256:7a7038e5b3646aaf151ee8375ddee42408379275d2c11b413931e4e1b597be7e",
      "boot_wait": "5s",
      "disk_size": 1,
      "headless": true,
      "shutdown_command": "poweroff",
      "ssh_password": "vagrant",
      "ssh_port": 22,
      "ssh_timeout": "10s",
      "ssh_username": "root",
      "type": "vmware-iso"
    },
    {
      "name": "alpine312",
      "output_directory": "output/alpine312",
      "iso_url": "https://mirrors.edge.kernel.org/alpine/v3.12/releases/x86_64/alpine-virt-3.12.12-x86_64.iso",
      "iso_checksum": "sha256:f569f7a9d47c1310f4ec50155a479adf0e27c79239d981a33629b62fa4281b63",
      "boot_wait": "5s",
      "disk_size": 1,
      "headless": true,
      "shutdown_command": "poweroff",
      "ssh_password": "vagrant",
      "ssh_port": 22,
      "ssh_timeout": "10s",
      "ssh_username": "root",
      "type": "vmware-iso"
    },
    {
      "name": "arch",
      "output_directory": "output/arch",
      "iso_url": "https://mirrors.edge.kernel.org/archlinux/iso/latest/archlinux-2023.05.03-x86_64.iso",
      "iso_checksum": "sha256:329b00c3e8cf094a28688c50a066b5ac6352731ccdff467f9fd7155e52d36cec",
      "boot_wait": "5s",
      "disk_size": 1,
      "headless": true,
      "shutdown_command": "poweroff",
      "ssh_password": "vagrant",
      "ssh_port": 22,
      "ssh_timeout": "10s",
      "ssh_username": "root",
      "type": "vmware-iso"
    },
    {
      "name": "centos6",
      "output_directory": "output/centos6",
      "iso_url": "https://vault.centos.org/6.10/isos/x86_64/CentOS-6.10-x86_64-minimal.iso",
      "iso_checksum": "sha256:7c0dee2a0494dabd84809b72ddb4b761f9ef92b78a506aef709b531c54d30770",
      "boot_wait": "5s",
      "disk_size": 1,
      "headless": true,
      "shutdown_command": "poweroff",
      "ssh_password": "vagrant",
      "ssh_port": 22,
      "ssh_timeout": "10s",
      "ssh_username": "root",
      "type": "vmware-iso"
    },
    {
      "name": "centos7",
      "output_directory": "output/centos7",
      "iso_url": "https://mirrors.edge.kernel.org/centos/7.9.2009/isos/x86_64/CentOS-7-x86_64-Minimal-2009.iso",
      "iso_checksum": "sha256:07b94e6b1a0b0260b94c83d6bb76b26bf7a310dc78d7a9c7432809fb9bc6194a",
      "boot_wait": "5s",
      "disk_size": 1,
      "headless": true,
      "shutdown_command": "poweroff",
      "ssh_password": "vagrant",
      "ssh_port": 22,
      "ssh_timeout": "10s",
      "ssh_username": "root",
      "type": "vmware-iso"
    },
    {
      "name": "centos8",
      "output_directory": "output/centos8",
      "iso_url": "https://vault.centos.org/8.5.2111/isos/x86_64/CentOS-8.5.2111-x86_64-boot.iso",
      "iso_checksum": "sha256:9602c69c52d93f51295c0199af395ca0edbe35e36506e32b8e749ce6c8f5b60a",
      "boot_wait": "5s",
      "disk_size": 1,
      "headless": true,
      "shutdown_command": "poweroff",
      "ssh_password": "vagrant",
      "ssh_port": 22,
      "ssh_timeout": "10s",
      "ssh_username": "root",
      "type": "vmware-iso"
    },
    {
      "name": "debian8",
      "output_directory": "output/debian8",
      "iso_url": "https://cdimage.debian.org/cdimage/archive/8.11.1/amd64/iso-dvd/debian-8.11.1-amd64-DVD-1.iso",
      "iso_checksum": "sha256:a3bd67cd363b609e1340cea06a666cb476b63fc79abf4380c0475dd1b6dc8a31",
      "boot_wait": "5s",
      "disk_size": 1,
      "headless": true,
      "shutdown_command": "poweroff",
      "ssh_password": "vagrant",
      "ssh_port": 22,
      "ssh_timeout": "10s",
      "ssh_username": "root",
      "type": "vmware-iso"
    },
    {
      "name": "debian8-x32",
      "output_directory": "output/debian8-x32",
      "iso_url": "https://cdimage.debian.org/cdimage/archive/8.11.1/i386/iso-dvd/debian-8.11.1-i386-DVD-1.iso",
      "iso_checksum": "sha256:06b6faafa5c2c74a2bbaa398589a0448ff0c2755fe9bab4c1013f40781fb4a2a",
      "boot_wait": "5s",
      "disk_size": 1,
      "headless": true,
      "shutdown_command": "poweroff",
      "ssh_password": "vagrant",
      "ssh_port": 22,
      "ssh_timeout": "10s",
      "ssh_username": "root",
      "type": "vmware-iso"
    },
    {
      "name": "debian9",
      "output_directory": "output/debian9",
      "iso_url": "https://cdimage.debian.org/cdimage/archive/9.13.0/amd64/iso-cd/debian-9.13.0-amd64-netinst.iso",
      "iso_checksum": "sha256:71c7e9eb292acc880f84605b1ca2b997f25737fe0a43fc9586f61d35cd2eb43b",
      "boot_wait": "5s",
      "disk_size": 1,
      "headless": true,
      "shutdown_command": "poweroff",
      "ssh_password": "vagrant",
      "ssh_port": 22,
      "ssh_timeout": "10s",
      "ssh_username": "root",
      "type": "vmware-iso"
    },
    {
      "name": "debian9-x32",
      "output_directory": "output/debian9-x32",
      "iso_url": "https://cdimage.debian.org/cdimage/archive/9.13.0/i386/iso-cd/debian-9.13.0-i386-netinst.iso",
      "iso_checksum": "sha256:27de998af87007bf5daa3030d3863d3ef801b948c29f5bbce232be4f928eedba",
      "boot_wait": "5s",
      "disk_size": 1,
      "headless": true,
      "shutdown_command": "poweroff",
      "ssh_password": "vagrant",
      "ssh_port": 22,
      "ssh_timeout": "10s",
      "ssh_username": "root",
      "type": "vmware-iso"
    },
    {
      "name": "debian10",
      "output_directory": "output/debian10",
      "iso_url": "https://cdimage.debian.org/cdimage/archive/10.13.0/amd64/iso-cd/debian-10.13.0-amd64-netinst.iso",
      "iso_checksum": "sha256:75aa64071060402a594dcf1e14afd669ca0f8bf757b56d4c9c1a31b8f7c8f931",
      "boot_wait": "5s",
      "disk_size": 1,
      "headless": true,
      "shutdown_command": "poweroff",
      "ssh_password": "vagrant",
      "ssh_port": 22,
      "ssh_timeout": "10s",
      "ssh_username": "root",
      "type": "vmware-iso"
    },
    {
      "name": "debian10-x32",
      "output_directory": "output/debian10-x32",
      "iso_url": "https://cdimage.debian.org/cdimage/archive/10.13.0/i386/iso-cd/debian-10.13.0-i386-netinst.iso",
      "iso_checksum": "sha256:af48af8142c6a162e15d70d1f7c77d205ab86e070270939961d0c3021557179f",
      "boot_wait": "5s",
      "disk_size": 1,
      "headless": true,
      "shutdown_command": "poweroff",
      "ssh_password": "vagrant",
      "ssh_port": 22,
      "ssh_timeout": "10s",
      "ssh_username": "root",
      "type": "vmware-iso"
    },
    {
      "name": "devuan1",
      "output_directory": "output/devuan1",
      "iso_url": "https://mirror.leaseweb.com/devuan/devuan_jessie/installer-iso/devuan_jessie_1.0.0_amd64_NETINST.iso",
      "iso_checksum": "sha256:70c6abe544ec59b0d0882c666ca0377be1b6c218655dac1f61b2c7e88c9b3d9f",
      "boot_wait": "5s",
      "disk_size": 1,
      "headless": true,
      "shutdown_command": "poweroff",
      "ssh_password": "vagrant",
      "ssh_port": 22,
      "ssh_timeout": "10s",
      "ssh_username": "root",
      "type": "vmware-iso"
    },
    {
      "name": "devuan2",
      "output_directory": "output/devuan2",
      "iso_url": "https://mirror.leaseweb.com/devuan/devuan_ascii/installer-iso/devuan_ascii_2.1_amd64_netinst.iso",
      "iso_checksum": "sha256:9aa6de460fb944ddfec8c79306974a522be166e4d296e9673f083f9e1cc6c56c",
      "boot_wait": "5s",
      "disk_size": 1,
      "headless": true,
      "shutdown_command": "poweroff",
      "ssh_password": "vagrant",
      "ssh_port": 22,
      "ssh_timeout": "10s",
      "ssh_username": "root",
      "type": "vmware-iso"
    },
    {
      "name": "devuan3",
      "output_directory": "output/devuan3",
      "iso_url": "https://mirror.leaseweb.com/devuan/devuan_beowulf/installer-iso/devuan_beowulf_3.1.1_amd64_netinstall.iso",
      "iso_checksum": "sha256:1723cbbeb1aee26a54e1370b688e7dc03921402348d2a60086c58c18cd9cf24b",
      "boot_wait": "5s",
      "disk_size": 1,
      "headless": true,
      "shutdown_command": "poweroff",
      "ssh_password": "vagrant",
      "ssh_port": 22,
      "ssh_timeout": "10s",
      "ssh_username": "root",
      "type": "vmware-iso"
    },
    {
      "name": "dragonflybsd5",
      "output_directory": "output/dragonflybsd5",
      "iso_url": "https://mirrors.lavabit.com/dragonflybsd/dfly-x86_64-5.8.3_REL.iso",
      "iso_checksum": "sha256:8c169e787822ab743e0ee7ddb97c2f4181316ebcd7f7a3e82a085c30f3ea29b5",
      "boot_wait": "5s",
      "disk_size": 1,
      "headless": true,
      "shutdown_command": "poweroff",
      "ssh_password": "vagrant",
      "ssh_port": 22,
      "ssh_timeout": "10s",
      "ssh_username": "root",
      "type": "vmware-iso"
    },
    {
      "name": "dragonflybsd5-hyperv",
      "output_directory": "output/dragonflybsd5-hyperv",
      "iso_url": "https://archive.org/download/dfly-x86_64-5.6.3_REL/dfly-x86_64-5.6.3_REL.iso",
      "iso_checksum": "sha256:7f95358f8c359ebedf433cd0604096fa1bc1f86b6188cbd9550b146f9f5478b8",
      "boot_wait": "5s",
      "disk_size": 1,
      "headless": true,
      "shutdown_command": "poweroff",
      "ssh_password": "vagrant",
      "ssh_port": 22,
      "ssh_timeout": "10s",
      "ssh_username": "root",
      "type": "vmware-iso"
    },
    {
      "name": "fedora25",
      "output_directory": "output/fedora25",
      "iso_url": "https://archives.fedoraproject.org/pub/archive/fedora/linux/releases/25/Server/x86_64/iso/Fedora-Server-netinst-x86_64-25-1.3.iso",
      "iso_checksum": "sha256:86bc3694f4938382753d1e9536f2140a6c9c1978207766340c679a89509073c7",
      "boot_wait": "5s",
      "disk_size": 1,
      "headless": true,
      "shutdown_command": "poweroff",
      "ssh_password": "vagrant",
      "ssh_port": 22,
      "ssh_timeout": "10s",
      "ssh_username": "root",
      "type": "vmware-iso"
    },
    {
      "name": "fedora26",
      "output_directory": "output/fedora26",
      "iso_url": "https://archives.fedoraproject.org/pub/archive/fedora/linux/releases/26/Server/x86_64/iso/Fedora-Server-netinst-x86_64-26-1.5.iso",
      "iso_checksum": "sha256:e260921ef5c7bd5ee2a7b2f2f1156af6483014c73984e4cf37f2b6690e0155e5",
      "boot_wait": "5s",
      "disk_size": 1,
      "headless": true,
      "shutdown_command": "poweroff",
      "ssh_password": "vagrant",
      "ssh_port": 22,
      "ssh_timeout": "10s",
      "ssh_username": "root",
      "type": "vmware-iso"
    },
    {
      "name": "fedora27",
      "output_directory": "output/fedora27",
      "iso_url": "https://archives.fedoraproject.org/pub/archive/fedora/linux/releases/27/Server/x86_64/iso/Fedora-Server-netinst-x86_64-27-1.6.iso",
      "iso_checksum": "sha256:2b93836c38833b26891345388ff5ddea60529b27a616b4539d432a3520d1c90b",
      "boot_wait": "5s",
      "disk_size": 1,
      "headless": true,
      "shutdown_command": "poweroff",
      "ssh_password": "vagrant",
      "ssh_port": 22,
      "ssh_timeout": "10s",
      "ssh_username": "root",
      "type": "vmware-iso"
    },
    {
      "name": "fedora28",
      "output_directory": "output/fedora28",
      "iso_url": "https://archives.fedoraproject.org/pub/archive/fedora/linux/releases/28/Server/x86_64/iso/Fedora-Server-netinst-x86_64-28-1.1.iso",
      "iso_checksum": "sha256:ea1efdc692356b3346326f82e2f468903e8da59324fdee8b10eac4fea83f23fe",
      "boot_wait": "5s",
      "disk_size": 1,
      "headless": true,
      "shutdown_command": "poweroff",
      "ssh_password": "vagrant",
      "ssh_port": 22,
      "ssh_timeout": "10s",
      "ssh_username": "root",
      "type": "vmware-iso"
    },
    {
      "name": "fedora29",
      "output_directory": "output/fedora29",
      "iso_url": "https://archives.fedoraproject.org/pub/archive/fedora/linux/releases/29/Server/x86_64/iso/Fedora-Server-netinst-x86_64-29-1.2.iso",
      "iso_checksum": "sha256:aa7fb0e6e5b71774ebdaab0dae76bdd9246a5bc7aedc28b7f1103aaaf9750654",
      "boot_wait": "5s",
      "disk_size": 1,
      "headless": true,
      "shutdown_command": "poweroff",
      "ssh_password": "vagrant",
      "ssh_port": 22,
      "ssh_timeout": "10s",
      "ssh_username": "root",
      "type": "vmware-iso"
    },
    {
      "name": "fedora30",
      "output_directory": "output/fedora30",
      "iso_url": "https://archives.fedoraproject.org/pub/archive/fedora/linux/releases/30/Server/x86_64/iso/Fedora-Server-netinst-x86_64-30-1.2.iso",
      "iso_checksum": "sha256:5e4eac4566d8c572bfb3bcf54b7d6c82006ec3c6c882a2c9235c6d3494d7b100",
      "boot_wait": "5s",
      "disk_size": 1,
      "headless": true,
      "shutdown_command": "poweroff",
      "ssh_password": "vagrant",
      "ssh_port": 22,
      "ssh_timeout": "10s",
      "ssh_username": "root",
      "type": "vmware-iso"
    },
    {
      "name": "fedora31",
      "output_directory": "output/fedora31",
      "iso_url": "https://archives.fedoraproject.org/pub/archive/fedora/linux/releases/31/Server/x86_64/iso/Fedora-Server-netinst-x86_64-31-1.9.iso",
      "iso_checksum": "sha256:5be8debd3e8fb4e86b9fbf67c7eb66ea598d2b7ad0c7ba8d505ce88067b43444",
      "boot_wait": "5s",
      "disk_size": 1,
      "headless": true,
      "shutdown_command": "poweroff",
      "ssh_password": "vagrant",
      "ssh_port": 22,
      "ssh_timeout": "10s",
      "ssh_username": "root",
      "type": "vmware-iso"
    },
    {
      "name": "fedora32",
      "output_directory": "output/fedora32",
      "iso_url": "https://archives.fedoraproject.org/pub/archive/fedora/linux/releases/32/Server/x86_64/iso/Fedora-Server-netinst-x86_64-32-1.6.iso",
      "iso_checksum": "sha256:7f4afd2a26c718f9f15e4bbfd9c2e8849f81036d2a82a4e81fa4a313a833da9c",
      "boot_wait": "5s",
      "disk_size": 1,
      "headless": true,
      "shutdown_command": "poweroff",
      "ssh_password": "vagrant",
      "ssh_port": 22,
      "ssh_timeout": "10s",
      "ssh_username": "root",
      "type": "vmware-iso"
    },
    {
      "name": "fedora33",
      "output_directory": "output/fedora33",
      "iso_url": "https://archives.fedoraproject.org/pub/archive/fedora/linux/releases/33/Server/x86_64/iso/Fedora-Server-netinst-x86_64-33-1.2.iso",
      "iso_checksum": "sha256:1f1f018e78f0cc23d08db0c85952344ea5c200e67b672da5b07507c066a52ccf",
      "boot_wait": "5s",
      "disk_size": 1,
      "headless": true,
      "shutdown_command": "poweroff",
      "ssh_password": "vagrant",
      "ssh_port": 22,
      "ssh_timeout": "10s",
      "ssh_username": "root",
      "type": "vmware-iso"
    },
    {
      "name": "freebsd11",
      "output_directory": "output/freebsd11",
      "iso_url": "http://ftp-archive.freebsd.org/pub/FreeBSD-Archive/old-releases/ISO-IMAGES/11.4/FreeBSD-11.4-RELEASE-amd64-disc1.iso",
      "iso_checksum": "sha256:d76c1ded99b2c1005b1ff94cc0c811fbcd8a2d04196432009ab5f203c2146914",
      "boot_wait": "5s",
      "disk_size": 1,
      "headless": true,
      "shutdown_command": "poweroff",
      "ssh_password": "vagrant",
      "ssh_port": 22,
      "ssh_timeout": "10s",
      "ssh_username": "root",
      "type": "vmware-iso"
    },
    {
      "name": "freebsd12",
      "output_directory": "output/freebsd12",
      "iso_url": "https://download.freebsd.org/ftp/releases/ISO-IMAGES/12.4/FreeBSD-12.4-RELEASE-amd64-disc1.iso",
      "iso_checksum": "sha256:606435637b76991f96df68f561badf03266f3d5452e9f72ed9b130d96b188800",
      "boot_wait": "5s",
      "disk_size": 1,
      "headless": true,
      "shutdown_command": "poweroff",
      "ssh_password": "vagrant",
      "ssh_port": 22,
      "ssh_timeout": "10s",
      "ssh_username": "root",
      "type": "vmware-iso"
    },
    {
      "name": "gentoo",
      "output_directory": "output/gentoo",
      "iso_url": "https://mirrors.edge.kernel.org/gentoo/releases/amd64/autobuilds/current-install-amd64-minimal/install-amd64-minimal-20230507T164658Z.iso",
      "iso_checksum": "sha256:ff427e1aba1d1250679305d9b4f12f6bf6afb8df8d137900da5fcb343d0de59b",
      "boot_wait": "5s",
      "disk_size": 1,
      "headless": true,
      "shutdown_command": "poweroff",
      "ssh_password": "vagrant",
      "ssh_port": 22,
      "ssh_timeout": "10s",
      "ssh_username": "root",
      "type": "vmware-iso"
    },
    {
      "name": "hardenedbsd11",
      "output_directory": "output/hardenedbsd11",
      "iso_url": "https://dk-01.installer.hardenedbsd.org/pub/HardenedBSD/releases/amd64/amd64/ISO-IMAGES/hardenedbsd-11-stable-20190205-1/HardenedBSD-11-STABLE-v1100056.13-amd64-disc1.iso",
      "iso_checksum": "sha256:8b2c90dc41ec68b561028af885eecb66bfd36223970d1c594923d1d54bf83467",
      "boot_wait": "5s",
      "disk_size": 1,
      "headless": true,
      "shutdown_command": "poweroff",
      "ssh_password": "vagrant",
      "ssh_port": 22,
      "ssh_timeout": "10s",
      "ssh_username": "root",
      "type": "vmware-iso"
    },
    {
      "name": "hardenedbsd12",
      "output_directory": "output/hardenedbsd12",
      "iso_url": "https://dk-01.installer.hardenedbsd.org/pub/HardenedBSD/releases/amd64/amd64/ISO-IMAGES/hardenedbsd-12-stable-20190807-1/HardenedBSD-12-STABLE-v1200059.3-amd64-disc1.iso",
      "iso_checksum": "sha256:029225eaf92ba8e7ed7a7395f45492d09bc9a949488ecb9a5ca54df7c9f89661",
      "boot_wait": "5s",
      "disk_size": 1,
      "headless": true,
      "shutdown_command": "poweroff",
      "ssh_password": "vagrant",
      "ssh_port": 22,
      "ssh_timeout": "10s",
      "ssh_username": "root",
      "type": "vmware-iso"
    },
    {
      "name": "netbsd8",
      "output_directory": "output/netbsd8",
      "iso_url": "https://ftp.netbsd.org/pub/NetBSD/iso/8.2/NetBSD-8.2-amd64.iso",
      "iso_checksum": "sha256:55d03c51d5b94cf7f03a29c1ee7e9f49d6b0ec4c2e1b1a2523c03956b70a1841",
      "boot_wait": "5s",
      "disk_size": 1,
      "headless": true,
      "shutdown_command": "poweroff",
      "ssh_password": "vagrant",
      "ssh_port": 22,
      "ssh_timeout": "10s",
      "ssh_username": "root",
      "type": "vmware-iso"
    },
    {
      "name": "netbsd9",
      "output_directory": "output/netbsd9",
      "iso_url": "https://ftp.netbsd.org/pub/NetBSD/iso/9.3/NetBSD-9.3-amd64.iso",
      "iso_checksum": "sha256:7e7f03bfd0584480cd11ed8833963310e34361d105498a028a2ebf3c10354171",
      "boot_wait": "5s",
      "disk_size": 1,
      "headless": true,
      "shutdown_command": "poweroff",
      "ssh_password": "vagrant",
      "ssh_port": 22,
      "ssh_timeout": "10s",
      "ssh_username": "root",
      "type": "vmware-iso"
    },
    {
      "name": "openbsd6",
      "output_directory": "output/openbsd6",
      "iso_url": "https://mirrors.lavabit.com/openbsd/6.9/amd64/cd69.iso",
      "iso_checksum": "sha256:b391350d72a4fcab550033c830a17612cff65ebdb6de428732d9b15f780bf9c2",
      "boot_wait": "5s",
      "disk_size": 1,
      "headless": true,
      "shutdown_command": "poweroff",
      "ssh_password": "vagrant",
      "ssh_port": 22,
      "ssh_timeout": "10s",
      "ssh_username": "root",
      "type": "vmware-iso"
    },
    {
      "name": "opensuse15",
      "output_directory": "output/opensuse15",
      "iso_url": "https://download.opensuse.org/distribution/leap/15.4/iso/openSUSE-Leap-15.4-DVD-x86_64-Build243.2-Media.iso",
      "iso_checksum": "sha256:4683345f242397c7fd7d89a50731a120ffd60a24460e21d2634e783b3c169695",
      "boot_wait": "5s",
      "disk_size": 1,
      "headless": true,
      "shutdown_command": "poweroff",
      "ssh_password": "vagrant",
      "ssh_port": 22,
      "ssh_timeout": "10s",
      "ssh_username": "root",
      "type": "vmware-iso"
    },
    {
      "name": "opensuse42",
      "output_directory": "output/opensuse42",
      "iso_url": "https://ftp5.gwdg.de/pub/opensuse/discontinued/distribution/leap/42.3/iso/openSUSE-Leap-42.3-NET-x86_64.iso",
      "iso_checksum": "sha256:d1a17116cf33a5582b83ef479d7b151b33938e60f07eebc544abf162e2aa5c12",
      "boot_wait": "5s",
      "disk_size": 1,
      "headless": true,
      "shutdown_command": "poweroff",
      "ssh_password": "vagrant",
      "ssh_port": 22,
      "ssh_timeout": "10s",
      "ssh_username": "root",
      "type": "vmware-iso"
    },
    {
      "name": "oracle7",
      "output_directory": "output/oracle7",
      "iso_url": "https://yum.oracle.com/ISOS/OracleLinux/OL7/u9/x86_64/x86_64-boot-uek.iso",
      "iso_checksum": "sha256:6da0323423f3a52d20d1021c2651885052319ca4ace7532859d8d20640829004",
      "boot_wait": "5s",
      "disk_size": 1,
      "headless": true,
      "shutdown_command": "poweroff",
      "ssh_password": "vagrant",
      "ssh_port": 22,
      "ssh_timeout": "10s",
      "ssh_username": "root",
      "type": "vmware-iso"
    },
    {
      "name": "oracle8",
      "output_directory": "output/oracle8",
      "iso_url": "https://yum.oracle.com/ISOS/OracleLinux/OL8/u7/x86_64/x86_64-boot-uek.iso",
      "iso_checksum": "sha256:d88b649f384a08cbb13e87e3ab0fb4088a1c8c601e3678abbb916c700229f80e",
      "boot_wait": "5s",
      "disk_size": 1,
      "headless": true,
      "shutdown_command": "poweroff",
      "ssh_password": "vagrant",
      "ssh_port": 22,
      "ssh_timeout": "10s",
      "ssh_username": "root",
      "type": "vmware-iso"
    },
    {
      "name": "rhel6",
      "output_directory": "output/rhel6",
      "iso_url": "https://archive.org/download/rhel-server-6.10-x86_64-dvd/rhel-server-6.10-x86_64-dvd.iso",
      "iso_checksum": "sha256:1e15f9202d2cdd4b2bdf9d6503a8543347f0cb8cc06ba9a0dfd2df4fdef5c727",
      "boot_wait": "5s",
      "disk_size": 1,
      "headless": true,
      "shutdown_command": "poweroff",
      "ssh_password": "vagrant",
      "ssh_port": 22,
      "ssh_timeout": "10s",
      "ssh_username": "root",
      "type": "vmware-iso"
    },
    {
      "name": "rhel7",
      "output_directory": "output/rhel7",
      "iso_url": "https://archive.org/download/rhel-server-7.9-x86_64-dvd/rhel-server-7.9-x86_64-dvd.iso",
      "iso_checksum": "sha256:19d653ce2f04f202e79773a0cbeda82070e7527557e814ebbce658773fbe8191",
      "boot_wait": "5s",
      "disk_size": 1,
      "headless": true,
      "shutdown_command": "poweroff",
      "ssh_password": "vagrant",
      "ssh_port": 22,
      "ssh_timeout": "10s",
      "ssh_username": "root",
      "type": "vmware-iso"
    },
    {
      "name": "rhel8",
      "output_directory": "output/rhel8",
      "iso_url": "https://archive.org/download/rhel-8.7/rhel-8.7-x86_64-dvd.iso",
      "iso_checksum": "sha256:a6a7418a75d721cc696d3cbdd648b5248808e7fef0f8742f518e43b46fa08139",
      "boot_wait": "5s",
      "disk_size": 1,
      "headless": true,
      "shutdown_command": "poweroff",
      "ssh_password": "vagrant",
      "ssh_port": 22,
      "ssh_timeout": "10s",
      "ssh_username": "root",
      "type": "vmware-iso"
    },
    {
      "name": "ubuntu1604",
      "output_directory": "output/ubuntu1604",
      "iso_url": "https://mirrors.edge.kernel.org/ubuntu-releases/16.04.7/ubuntu-16.04.7-server-amd64.iso",
      "iso_checksum": "sha256:b23488689e16cad7a269eb2d3a3bf725d3457ee6b0868e00c8762d3816e25848",
      "boot_wait": "5s",
      "disk_size": 1,
      "headless": true,
      "shutdown_command": "poweroff",
      "ssh_password": "vagrant",
      "ssh_port": 22,
      "ssh_timeout": "10s",
      "ssh_username": "root",
      "type": "vmware-iso"
    },
    {
      "name": "ubuntu1610",
      "output_directory": "output/ubuntu1610",
      "iso_url": "https://old-releases.ubuntu.com/releases/16.10/ubuntu-16.10-server-amd64.iso",
      "iso_checksum": "sha256:72b0d421da77f1e0c549b4efe6fc6c184e9909d6792f0d1e59b56d63e9705659",
      "boot_wait": "5s",
      "disk_size": 1,
      "headless": true,
      "shutdown_command": "poweroff",
      "ssh_password": "vagrant",
      "ssh_port": 22,
      "ssh_timeout": "10s",
      "ssh_username": "root",
      "type": "vmware-iso"
    },
    {
      "name": "ubuntu1704",
      "output_directory": "output/ubuntu1704",
      "iso_url": "https://old-releases.ubuntu.com/releases/17.04/ubuntu-17.04-server-amd64.iso",
      "iso_checksum": "sha256:ca5d9a8438e2434b9a3ac2be67b5c5fa2c1f8e3e40b954519462935195464034",
      "boot_wait": "5s",
      "disk_size": 1,
      "headless": true,
      "shutdown_command": "poweroff",
      "ssh_password": "vagrant",
      "ssh_port": 22,
      "ssh_timeout": "10s",
      "ssh_username": "root",
      "type": "vmware-iso"
    },
    {
      "name": "ubuntu1710",
      "output_directory": "output/ubuntu1710",
      "iso_url": "https://old-releases.ubuntu.com/releases/17.10/ubuntu-17.10.1-server-amd64.iso",
      "iso_checksum": "sha256:8ff73f1b622276758475c3bd5190b382774626de5a82c50930519381f6c3a3f8",
      "boot_wait": "5s",
      "disk_size": 1,
      "headless": true,
      "shutdown_command": "poweroff",
      "ssh_password": "vagrant",
      "ssh_port": 22,
      "ssh_timeout": "10s",
      "ssh_username": "root",
      "type": "vmware-iso"
    },
    {
      "name": "ubuntu1804",
      "output_directory": "output/ubuntu1804",
      "iso_url": "https://cdimage.ubuntu.com/ubuntu/releases/18.04.6/release/ubuntu-18.04.6-server-amd64.iso",
      "iso_checksum": "sha256:f5cbb8104348f0097a8e513b10173a07dbc6684595e331cb06f93f385d0aecf6",
      "boot_wait": "5s",
      "disk_size": 1,
      "headless": true,
      "shutdown_command": "poweroff",
      "ssh_password": "vagrant",
      "ssh_port": 22,
      "ssh_timeout": "10s",
      "ssh_username": "root",
      "type": "vmware-iso"
    },
    {
      "name": "ubuntu1810",
      "output_directory": "output/ubuntu1810",
      "iso_url": "https://old-releases.ubuntu.com/releases/18.10/ubuntu-18.10-server-amd64.iso",
      "iso_checksum": "sha256:cf9250781dadd919f23c9d9612212cad653e35fccc2fbcf6853f67ad09e067ba",
      "boot_wait": "5s",
      "disk_size": 1,
      "headless": true,
      "shutdown_command": "poweroff",
      "ssh_password": "vagrant",
      "ssh_port": 22,
      "ssh_timeout": "10s",
      "ssh_username": "root",
      "type": "vmware-iso"
    },
    {
      "name": "ubuntu1904",
      "output_directory": "output/ubuntu1904",
      "iso_url": "https://old-releases.ubuntu.com/releases/19.04/ubuntu-19.04-server-amd64.iso",
      "iso_checksum": "sha256:7e8a0d07522f591dfee9bc9fcd7c05466763161e6cb0117906655bce1750b2fa",
      "boot_wait": "5s",
      "disk_size": 1,
      "headless": true,
      "shutdown_command": "poweroff",
      "ssh_password": "vagrant",
      "ssh_port": 22,
      "ssh_timeout": "10s",
      "ssh_username": "root",
      "type": "vmware-iso"
    },
    {
      "name": "ubuntu1910",
      "output_directory": "output/ubuntu1910",
      "iso_url": "https://archive.org/download/ubuntu-19.10-server-amd64/ubuntu-19.10-server-amd64.iso",
      "iso_checksum": "sha256:921fd8b271c04aa86a321cc35b40e677f9b85f7903bf2204efb2389b0f0a64c1",
      "boot_wait": "5s",
      "disk_size": 1,
      "headless": true,
      "shutdown_command": "poweroff",
      "ssh_password": "vagrant",
      "ssh_port": 22,
      "ssh_timeout": "10s",
      "ssh_username": "root",
      "type": "vmware-iso"
    },
    {
      "name": "ubuntu2004",
      "output_directory": "output/ubuntu2004",
      "iso_url": "https://cdimage.ubuntu.com/ubuntu-legacy-server/releases/20.04/release/ubuntu-20.04.1-legacy-server-amd64.iso",
      "iso_checksum": "sha256:f11bda2f2caed8f420802b59f382c25160b114ccc665dbac9c5046e7fceaced2",
      "boot_wait": "5s",
      "disk_size": 1,
      "headless": true,
      "shutdown_command": "poweroff",
      "ssh_password": "vagrant",
      "ssh_port": 22,
      "ssh_timeout": "10s",
      "ssh_username": "root",
      "type": "vmware-iso"
    },
    {
      "name": "ubuntu2010",
      "output_directory": "output/ubuntu2010",
      "iso_url": "https://old-releases.ubuntu.com/releases/20.10/ubuntu-20.10-live-server-amd64.iso",
      "iso_checksum": "sha256:defdc1ad3af7b661fe2b4ee861fb6fdb5f52039389ef56da6efc05e6adfe3d45",
      "boot_wait": "5s",
      "disk_size": 1,
      "headless": true,
      "shutdown_command": "poweroff",
      "ssh_password": "vagrant",
      "ssh_port": 22,
      "ssh_timeout": "10s",
      "ssh_username": "root",
      "type": "vmware-iso"
    },
    {
      "name": "virtualbox-5-1-14",
      "output_directory": "output/virtualbox-5-1-14",
      "iso_url": "https://download.virtualbox.org/virtualbox/5.1.14/VBoxGuestAdditions_5.1.14.iso",
      "iso_checksum": "sha256:1b206b76050dccd3ed979307230f9ddea79551e1c0aba93faee77416733cdc8a",
      "boot_wait": "5s",
      "disk_size": 1,
      "headless": true,
      "shutdown_command": "poweroff",
      "ssh_password": "vagrant",
      "ssh_port": 22,
      "ssh_timeout": "10s",
      "ssh_username": "root",
      "type": "vmware-iso"
    },
    {
      "name": "virtualbox-5-1-38",
      "output_directory": "output/virtualbox-5-1-38",
      "iso_url": "https://download.virtualbox.org/virtualbox/5.1.38/VBoxGuestAdditions_5.1.38.iso",
      "iso_checksum": "sha256:0e7ee2c78ebf7cd0d3a933d51148bef04a64f64fb27ccf70d59cddf9ca1e517a",
      "boot_wait": "5s",
      "disk_size": 1,
      "headless": true,
      "shutdown_command": "poweroff",
      "ssh_password": "vagrant",
      "ssh_port": 22,
      "ssh_timeout": "10s",
      "ssh_username": "root",
      "type": "vmware-iso"
    },
    {
      "name": "virtualbox-5-2-44",
      "output_directory": "output/virtualbox-5-2-44",
      "iso_url": "https://download.virtualbox.org/virtualbox/5.2.44/VBoxGuestAdditions_5.2.44.iso",
      "iso_checksum": "sha256:9883ee443a309f4ffa1d5dee2833f9e35ced598686c36d159f410e5edbac1ca4",
      "boot_wait": "5s",
      "disk_size": 1,
      "headless": true,
      "shutdown_command": "poweroff",
      "ssh_password": "vagrant",
      "ssh_port": 22,
      "ssh_timeout": "10s",
      "ssh_username": "root",
      "type": "vmware-iso"
    },
    {
      "name": "virtualbox-6-1-30",
      "output_directory": "output/virtualbox-6-1-30",
      "iso_url": "https://download.virtualbox.org/virtualbox/6.1.30/VBoxGuestAdditions_6.1.30.iso",
      "iso_checksum": "d324d2d09d8dd00b1eb3ef3d80ab2e1726998421d13adc0d2a90e05d355aaa5c",
      "boot_wait": "5s",
      "disk_size": 1,
      "headless": true,
      "shutdown_command": "poweroff",
      "ssh_password": "vagrant",
      "ssh_port": 22,
      "ssh_timeout": "10s",
      "ssh_username": "root",
      "type": "vmware-iso"
    },
    {
      "name": "virtualbox-6-1-36",
      "output_directory": "output/virtualbox-6-1-36",
      "iso_url": "https://download.virtualbox.org/virtualbox/6.1.36/VBoxGuestAdditions_6.1.36.iso",
      "iso_checksum": "c987cdc8c08c579f56d921c85269aeeac3faf636babd01d9461ce579c9362cdd",
      "boot_wait": "5s",
      "disk_size": 1,
      "headless": true,
      "shutdown_command": "poweroff",
      "ssh_password": "vagrant",
      "ssh_port": 22,
      "ssh_timeout": "10s",
      "ssh_username": "root",
      "type": "vmware-iso"
    },
    {
      "name": "virtualbox-6-1-40",
      "output_directory": "output/virtualbox-6-1-40",
      "iso_url": "https://download.virtualbox.org/virtualbox/6.1.40/VBoxGuestAdditions_6.1.40.iso",
      "iso_checksum": "d456c559926f1a8fdd7259056e0a50f12339fd494122cf30db7736e2032970c6",
      "boot_wait": "5s",
      "disk_size": 1,
      "headless": true,
      "shutdown_command": "poweroff",
      "ssh_password": "vagrant",
      "ssh_port": 22,
      "ssh_timeout": "10s",
      "ssh_username": "root",
      "type": "vmware-iso"
    },
    {
      "name": "virtualbox-7-0-2",
      "output_directory": "output/virtualbox-7-0-2",
      "iso_url": "https://download.virtualbox.org/virtualbox/7.0.2/VBoxGuestAdditions_7.0.2.iso",
      "iso_checksum": "9cf5413399f59cfa4ba9ed89a9295b1b2ef3b997cb526a100637b5c59a526872",
      "boot_wait": "5s",
      "disk_size": 1,
      "headless": true,
      "shutdown_command": "poweroff",
      "ssh_password": "vagrant",
      "ssh_port": 22,
      "ssh_timeout": "10s",
      "ssh_username": "root",
      "type": "vmware-iso"
    },
    {
      "name": "virtualbox-7-0-4",
      "output_directory": "output/virtualbox-7-0-4",
      "iso_url": "https://download.virtualbox.org/virtualbox/7.0.4/VBoxGuestAdditions_7.0.4.iso",
      "iso_checksum": "85908d49df9df685ae00806d4cf0d154791804651039a3839be8cc876fae1011",
      "boot_wait": "5s",
      "disk_size": 1,
      "headless": true,
      "shutdown_command": "poweroff",
      "ssh_password": "vagrant",
      "ssh_port": 22,
      "ssh_timeout": "10s",
      "ssh_username": "root",
      "type": "vmware-iso"
    },
    {
      "name": "alpine313",
      "output_directory": "output/alpine313",
      "iso_url": "https://mirrors.edge.kernel.org/alpine/v3.13/releases/x86_64/alpine-virt-3.13.12-x86_64.iso",
      "iso_checksum": "sha256:a1d440fc78d9bc1796980fd37ed24e5b7b74149d21df3d34b0ec745fc8f25128",
      "boot_wait": "5s",
      "disk_size": 1,
      "headless": true,
      "shutdown_command": "poweroff",
      "ssh_password": "vagrant",
      "ssh_port": 22,
      "ssh_timeout": "10s",
      "ssh_username": "root",
      "type": "vmware-iso"
    },
    {
      "name": "alpine314",
      "output_directory": "output/alpine314",
      "iso_url": "https://mirrors.edge.kernel.org/alpine/v3.14/releases/x86_64/alpine-virt-3.14.9-x86_64.iso",
      "iso_checksum": "sha256:27a3924c514fdf6459353d2ad12da864892ac9b51130e20f7898b5887c86be21",
      "boot_wait": "5s",
      "disk_size": 1,
      "headless": true,
      "shutdown_command": "poweroff",
      "ssh_password": "vagrant",
      "ssh_port": 22,
      "ssh_timeout": "10s",
      "ssh_username": "root",
      "type": "vmware-iso"
    },
    {
      "name": "ubuntu2104",
      "output_directory": "output/ubuntu2104",
      "iso_url": "https://old-releases.ubuntu.com/releases/21.04/ubuntu-21.04-live-server-amd64.iso",
      "iso_checksum": "sha256:e4089c47104375b59951bad6c7b3ee5d9f6d80bfac4597e43a716bb8f5c1f3b0",
      "boot_wait": "5s",
      "disk_size": 1,
      "headless": true,
      "shutdown_command": "poweroff",
      "ssh_password": "vagrant",
      "ssh_port": 22,
      "ssh_timeout": "10s",
      "ssh_username": "root",
      "type": "vmware-iso"
    },
    {
      "name": "rocky8",
      "output_directory": "output/rocky8",
      "iso_url": "https://ftp5.gwdg.de/pub/linux/rocky/8.7/isos/x86_64/Rocky-8.7-x86_64-boot.iso",
      "iso_checksum": "sha256:94402815f251d982e748dc3466517db13fa5f9ea58fad491dcbd2cc821a360a2",
      "boot_wait": "5s",
      "disk_size": 1,
      "headless": true,
      "shutdown_command": "poweroff",
      "ssh_password": "vagrant",
      "ssh_port": 22,
      "ssh_timeout": "10s",
      "ssh_username": "root",
      "type": "vmware-iso"
    },
    {
      "name": "alma8",
      "output_directory": "output/alma8",
      "iso_url": "https://dfw.mirror.rackspace.com/almalinux/8.7/isos/x86_64/AlmaLinux-8.7-x86_64-boot.iso",
      "iso_checksum": "sha256:a4fc8c53878e09f63849f2357228db9e2b547beea6f2b47758da2995bd59356e",
      "boot_wait": "5s",
      "disk_size": 1,
      "headless": true,
      "shutdown_command": "poweroff",
      "ssh_password": "vagrant",
      "ssh_port": 22,
      "ssh_timeout": "10s",
      "ssh_username": "root",
      "type": "vmware-iso"
    },
    {
      "name": "fedora34",
      "output_directory": "output/fedora34",
      "iso_url": "https://archives.fedoraproject.org/pub/archive/fedora/linux/releases/34/Server/x86_64/iso/Fedora-Server-netinst-x86_64-34-1.2.iso",
      "iso_checksum": "sha256:e1a38b9faa62f793ad4561b308c31f32876cfaaee94457a7a9108aaddaeec406",
      "boot_wait": "5s",
      "disk_size": 1,
      "headless": true,
      "shutdown_command": "poweroff",
      "ssh_password": "vagrant",
      "ssh_port": 22,
      "ssh_timeout": "10s",
      "ssh_username": "root",
      "type": "vmware-iso"
    },
    {
      "name": "freebsd13",
      "output_directory": "output/freebsd13",
      "iso_url": "https://download.freebsd.org/ftp/releases/ISO-IMAGES/13.1/FreeBSD-13.1-RELEASE-amd64-disc1.iso",
      "iso_checksum": "sha256:697d81653fa246b921ddfcf1d15562c55249cc727b11fa3e47f470e2cf2b6a40",
      "boot_wait": "5s",
      "disk_size": 1,
      "headless": true,
      "shutdown_command": "poweroff",
      "ssh_password": "vagrant",
      "ssh_port": 22,
      "ssh_timeout": "10s",
      "ssh_username": "root",
      "type": "vmware-iso"
    },
    {
      "name": "hardenedbsd13",
      "output_directory": "output/hardenedbsd13",
      "iso_url": "https://mirror.laylo.io/pub/hardenedbsd/13-stable/amd64/amd64/installer/build-9/disc1.iso",
      "iso_checksum": "sha256:51a4883c1a628fb13c33a9c5c6806a1f5bf527501c69a0668f4a1fa4b2f7892c",
      "boot_wait": "5s",
      "disk_size": 1,
      "headless": true,
      "shutdown_command": "poweroff",
      "ssh_password": "vagrant",
      "ssh_port": 22,
      "ssh_timeout": "10s",
      "ssh_username": "root",
      "type": "vmware-iso"
    },
    {
      "name": "debian11",
      "output_directory": "output/debian11",
      "iso_url": "https://cdimage.debian.org/cdimage/release/11.6.0/amd64/iso-cd/debian-11.6.0-amd64-netinst.iso",
      "iso_checksum": "sha256:e482910626b30f9a7de9b0cc142c3d4a079fbfa96110083be1d0b473671ce08d",
      "boot_wait": "5s",
      "disk_size": 1,
      "headless": true,
      "shutdown_command": "poweroff",
      "ssh_password": "vagrant",
      "ssh_port": 22,
      "ssh_timeout": "10s",
      "ssh_username": "root",
      "type": "vmware-iso"
    },
    {
      "name": "debian11-x32",
      "output_directory": "output/debian11-x32",
      "iso_url": "https://cdimage.debian.org/cdimage/release/11.6.0/i386/iso-cd/debian-11.6.0-i386-netinst.iso",
      "iso_checksum": "sha256:e6369838b9a59db641246fbb134840b84f2d315b89bd2f912d69a5f7c08c2197",
      "boot_wait": "5s",
      "disk_size": 1,
      "headless": true,
      "shutdown_command": "poweroff",
      "ssh_password": "vagrant",
      "ssh_port": 22,
      "ssh_timeout": "10s",
      "ssh_username": "root",
      "type": "vmware-iso"
    },
    {
      "name": "openbsd7",
      "output_directory": "output/openbsd7",
      "iso_url": "https://ftp.nluug.nl/OpenBSD/7.2/amd64/cd72.iso",
      "iso_checksum": "sha256:041f42e2692e609bfeabda71400100649af8f0aace12a5097794c3a868ff77ec",
      "boot_wait": "5s",
      "disk_size": 1,
      "headless": true,
      "shutdown_command": "poweroff",
      "ssh_password": "vagrant",
      "ssh_port": 22,
      "ssh_timeout": "10s",
      "ssh_username": "root",
      "type": "vmware-iso"
    },
    {
      "name": "ubuntu2110",
      "output_directory": "output/ubuntu2110",
      "iso_url": "https://old-releases.ubuntu.com/releases/21.10/ubuntu-21.10-live-server-amd64.iso",
      "iso_checksum": "sha256:e84f546dfc6743f24e8b1e15db9cc2d2c698ec57d9adfb852971772d1ce692d4",
      "boot_wait": "5s",
      "disk_size": 1,
      "headless": true,
      "shutdown_command": "poweroff",
      "ssh_password": "vagrant",
      "ssh_port": 22,
      "ssh_timeout": "10s",
      "ssh_username": "root",
      "type": "vmware-iso"
    },
    {
      "name": "alpine315",
      "output_directory": "output/alpine315",
      "iso_url": "https://mirrors.edge.kernel.org/alpine/v3.15/releases/x86_64/alpine-virt-3.15.7-x86_64.iso",
      "iso_checksum": "sha256:3c71a2cf95b419d73471c6e6e0d856750f3d3e74114771e4bd32b89b15a2cca9",
      "boot_wait": "5s",
      "disk_size": 1,
      "headless": true,
      "shutdown_command": "poweroff",
      "ssh_password": "vagrant",
      "ssh_port": 22,
      "ssh_timeout": "10s",
      "ssh_username": "root",
      "type": "vmware-iso"
    },
    {
      "name": "fedora35",
      "output_directory": "output/fedora35",
      "iso_url": "https://archives.fedoraproject.org/pub/archive/fedora/linux/releases/35/Server/x86_64/iso/Fedora-Server-netinst-x86_64-35-1.2.iso",
      "iso_checksum": "sha256:dd35f955dd5a7054213a0098c6ee737ff116aa3090fc6dbfe89d424b5c3552dd",
      "boot_wait": "5s",
      "disk_size": 1,
      "headless": true,
      "shutdown_command": "poweroff",
      "ssh_password": "vagrant",
      "ssh_port": 22,
      "ssh_timeout": "10s",
      "ssh_username": "root",
      "type": "vmware-iso"
    },
    {
      "name": "devuan4",
      "output_directory": "output/devuan4",
      "iso_url": "https://mirror.leaseweb.com/devuan/devuan_chimaera/installer-iso/devuan_chimaera_4.0.0_amd64_netinstall.iso",
      "iso_checksum": "sha256:0923470af430e3d582a635956bbe4c13abc18fbaa4704e6deef3b362833e0ef5",
      "boot_wait": "5s",
      "disk_size": 1,
      "headless": true,
      "shutdown_command": "poweroff",
      "ssh_password": "vagrant",
      "ssh_port": 22,
      "ssh_timeout": "10s",
      "ssh_username": "root",
      "type": "vmware-iso"
    },
    {
      "name": "ubuntu2204",
      "output_directory": "output/ubuntu2204",
      "iso_url": "https://releases.ubuntu.com/22.04/ubuntu-22.04.2-live-server-amd64.iso",
      "iso_checksum": "sha256:5e38b55d57d94ff029719342357325ed3bda38fa80054f9330dc789cd2d43931",
      "boot_wait": "5s",
      "disk_size": 1,
      "headless": true,
      "shutdown_command": "poweroff",
      "ssh_password": "vagrant",
      "ssh_port": 22,
      "ssh_timeout": "10s",
      "ssh_username": "root",
      "type": "vmware-iso"
    },
    {
      "name": "fedora36",
      "output_directory": "output/fedora36",
      "iso_url": "https://dl.fedoraproject.org/pub/fedora/linux/releases/36/Server/x86_64/iso/Fedora-Server-netinst-x86_64-36-1.5.iso",
      "iso_checksum": "sha256:421c4c6e23d72e4669a55e7710562287ecd9308b3d314329960f586b89ccca19",
      "boot_wait": "5s",
      "disk_size": 1,
      "headless": true,
      "shutdown_command": "poweroff",
      "ssh_password": "vagrant",
      "ssh_port": 22,
      "ssh_timeout": "10s",
      "ssh_username": "root",
      "type": "vmware-iso"
    },
    {
      "name": "rhel9",
      "output_directory": "output/rhel9",
      "iso_url": "https://archive.org/download/rhel-9.1/rhel-baseos-9.1-x86_64-dvd.iso",
      "iso_checksum": "sha256:d9dcae2b6e760d0f9dcf4a517bddc227d5fa3f213a8323592f4a07a05aa542a2",
      "boot_wait": "5s",
      "disk_size": 1,
      "headless": true,
      "shutdown_command": "poweroff",
      "ssh_password": "vagrant",
      "ssh_port": 22,
      "ssh_timeout": "10s",
      "ssh_username": "root",
      "type": "vmware-iso"
    },
    {
      "name": "centos8s",
      "output_directory": "output/centos8s",
      "iso_url": "https://mirrors.edge.kernel.org/centos/8-stream/isos/x86_64/CentOS-Stream-8-20230509.0-x86_64-boot.iso",
      "iso_checksum": "sha256:7396c9b92d1a22aa8979971cf2b1db2dcc6aabc1a3a44a4f21a7c765a22b4876",
      "boot_wait": "5s",
      "disk_size": 1,
      "headless": true,
      "shutdown_command": "poweroff",
      "ssh_password": "vagrant",
      "ssh_port": 22,
      "ssh_timeout": "10s",
      "ssh_username": "root",
      "type": "vmware-iso"
    },
    {
      "name": "centos9s",
      "output_directory": "output/centos9s",
      "iso_url": "https://dfw.mirror.rackspace.com/centos-stream/9-stream/BaseOS/x86_64/iso/CentOS-Stream-9-20230508.0-x86_64-boot.iso",
      "iso_checksum": "sha256:00f655b4e56045997ca74d2e76acc63f795a98aa58f51934a11d7a225ae8488b",
      "boot_wait": "5s",
      "disk_size": 1,
      "headless": true,
      "shutdown_command": "poweroff",
      "ssh_password": "vagrant",
      "ssh_port": 22,
      "ssh_timeout": "10s",
      "ssh_username": "root",
      "type": "vmware-iso"
    },
    {
      "name": "alpine316",
      "output_directory": "output/alpine316",
      "iso_url": "https://mirrors.edge.kernel.org/alpine/v3.16/releases/x86_64/alpine-virt-3.16.4-x86_64.iso",
      "iso_checksum": "sha256:dc8163713532f9025a12f0956a0070e325b1c0f0618080f8ba54ee05d62bd8b3",
      "boot_wait": "5s",
      "disk_size": 1,
      "headless": true,
      "shutdown_command": "poweroff",
      "ssh_password": "vagrant",
      "ssh_port": 22,
      "ssh_timeout": "10s",
      "ssh_username": "root",
      "type": "vmware-iso"
    },
    {
      "name": "alma9",
      "output_directory": "output/alma9",
      "iso_url": "https://dfw.mirror.rackspace.com/almalinux/9.1/isos/x86_64/AlmaLinux-9.1-x86_64-boot.iso",
      "iso_checksum": "sha256:9f22bd98c8930b1d0b2198ddd273c6647c09298e10a0167197a3f8c293d03090",
      "boot_wait": "5s",
      "disk_size": 1,
      "headless": true,
      "shutdown_command": "poweroff",
      "ssh_password": "vagrant",
      "ssh_port": 22,
      "ssh_timeout": "10s",
      "ssh_username": "root",
      "type": "vmware-iso"
    },
    {
      "name": "oracle9",
      "output_directory": "output/oracle9",
      "iso_url": "https://yum.oracle.com/ISOS/OracleLinux/OL9/u1/x86_64/OracleLinux-R9-U1-x86_64-boot.iso",
      "iso_checksum": "sha256:21878b1136acdaa588556ac83c7e8700a0604c310cd05c22eb6a8329a85dfddd",
      "boot_wait": "5s",
      "disk_size": 1,
      "headless": true,
      "shutdown_command": "poweroff",
      "ssh_password": "vagrant",
      "ssh_port": 22,
      "ssh_timeout": "10s",
      "ssh_username": "root",
      "type": "vmware-iso"
    },
    {
      "name": "rocky9",
      "output_directory": "output/rocky9",
      "iso_url": "https://ftp5.gwdg.de/pub/linux/rocky/9.1/isos/x86_64/Rocky-9.1-x86_64-boot.iso",
      "iso_checksum": "sha256:a36753d0efbea2f54a3dc7bfaa4dba95efe9aa3d6af331d5c5b147ea91240c21",
      "boot_wait": "5s",
      "disk_size": 1,
      "headless": true,
      "shutdown_command": "poweroff",
      "ssh_password": "vagrant",
      "ssh_port": 22,
      "ssh_timeout": "10s",
      "ssh_username": "root",
      "type": "vmware-iso"
    },
    {
      "name": "oracle6",
      "output_directory": "output/oracle6",
      "iso_url": "https://yum.oracle.com/ISOS/OracleLinux/OL6/u10/x86_64/OracleLinux-R6-U10-Server-x86_64-dvd.iso",
      "iso_checksum": "sha256:625044388ee60a031965a42a32f4c1de0c029268975edcd542fd14160e0dadcb",
      "boot_wait": "5s",
      "disk_size": 1,
      "headless": true,
      "shutdown_command": "poweroff",
      "ssh_password": "vagrant",
      "ssh_port": 22,
      "ssh_timeout": "10s",
      "ssh_username": "root",
      "type": "vmware-iso"
    },
    {
      "name": "ubuntu2210",
      "output_directory": "output/ubuntu2210",
      "iso_url": "https://releases.ubuntu.com/22.10/ubuntu-22.10-live-server-amd64.iso",
      "iso_checksum": "sha256:874452797430a94ca240c95d8503035aa145bd03ef7d84f9b23b78f3c5099aed",
      "boot_wait": "5s",
      "disk_size": 1,
      "headless": true,
      "shutdown_command": "poweroff",
      "ssh_password": "vagrant",
      "ssh_port": 22,
      "ssh_timeout": "10s",
      "ssh_username": "root",
      "type": "vmware-iso"
    },
    {
      "name": "fedora37",
      "output_directory": "output/fedora37",
      "iso_url": "https://dl.fedoraproject.org/pub/fedora/linux/releases/37/Server/x86_64/iso/Fedora-Server-netinst-x86_64-37-1.7.iso",
      "iso_checksum": "sha256:149d4bae999022b07bd40f8272f6208bc28884dad5110c63e915d37458e6abc0",
      "boot_wait": "5s",
      "disk_size": 1,
      "headless": true,
      "shutdown_command": "poweroff",
      "ssh_password": "vagrant",
      "ssh_port": 22,
      "ssh_timeout": "10s",
      "ssh_username": "root",
      "type": "vmware-iso"
    },
    {
      "name": "alpine317",
      "output_directory": "output/alpine317",
      "iso_url": "https://mirrors.edge.kernel.org/alpine/v3.17/releases/x86_64/alpine-virt-3.17.2-x86_64.iso",
      "iso_checksum": "sha256:96cd5a0a372b75e9d8607d2df8c3e604326f5c314c8c4f760ff901447a9a7746",
      "boot_wait": "5s",
      "disk_size": 1,
      "headless": true,
      "shutdown_command": "poweroff",
      "ssh_password": "vagrant",
      "ssh_port": 22,
      "ssh_timeout": "10s",
      "ssh_username": "root",
      "type": "vmware-iso"
    },
    {
      "name": "dragonflybsd6",
      "output_directory": "output/dragonflybsd6",
      "iso_url": "https://mirror-master.dragonflybsd.org/iso-images/dfly-x86_64-6.4.0_REL.iso",
      "iso_checksum": "sha256:20e4724a3cb838fec0148a4adbffd9bd57b3e6d759a6599d1149188a19c61265",
      "boot_wait": "5s",
      "disk_size": 1,
      "headless": true,
      "shutdown_command": "poweroff",
      "ssh_password": "vagrant",
      "ssh_port": 22,
      "ssh_timeout": "10s",
      "ssh_username": "root",
      "type": "vmware-iso"
    }
  ]
}
