{
  "builders": [
    {
      "name": "alpine35",
      "output_directory": "output/alpine35",
      "iso_url": "https://sjc.edge.kernel.org/alpine/v3.5/releases/x86_64/alpine-virt-3.5.3-x86_64.iso",
      "iso_checksum": "sha256:580bc6379e4b246d24b5e32d2637319a60ac953279b3e0df523222ef561bf2f5",
      "boot_wait": "5s",
      "disk_size": 1,
      "headless": true,
      "shutdown_command": "poweroff",
      "ssh_password": "vagrant",
      "ssh_port": 22,
      "ssh_timeout": "10s",
      "ssh_username": "root",
      "type": "vmware-iso"
    },
    {
      "name": "alpine35-hyperv",
      "output_directory": "output/alpine35-hyperv",
      "iso_url": "https://sjc.edge.kernel.org/alpine/v3.5/releases/x86_64/alpine-vanilla-3.5.3-x86_64.iso",
      "iso_checksum": "sha256:3cca39f256f6a11d89a1c89a54982e9806d3df0fd785dc66ff26d3c670c3d648",
      "boot_wait": "5s",
      "disk_size": 1,
      "headless": true,
      "shutdown_command": "poweroff",
      "ssh_password": "vagrant",
      "ssh_port": 22,
      "ssh_timeout": "10s",
      "ssh_username": "root",
      "type": "vmware-iso"
    },
    {
      "name": "alpine36",
      "output_directory": "output/alpine36",
      "iso_url": "https://sjc.edge.kernel.org/alpine/v3.6/releases/x86_64/alpine-virt-3.6.5-x86_64.iso",
      "iso_checksum": "sha256:b5936e27487e605ea3cbf040d444505ea7fd735021258d7b119faaa9b4b5b083",
      "boot_wait": "5s",
      "disk_size": 1,
      "headless": true,
      "shutdown_command": "poweroff",
      "ssh_password": "vagrant",
      "ssh_port": 22,
      "ssh_timeout": "10s",
      "ssh_username": "root",
      "type": "vmware-iso"
    },
    {
      "name": "alpine37",
      "output_directory": "output/alpine37",
      "iso_url": "https://sjc.edge.kernel.org/alpine/v3.7/releases/x86_64/alpine-virt-3.7.3-x86_64.iso",
      "iso_checksum": "sha256:2f7a23fc31a6f67348e5614597b23ab8d9340e8a0f4368e96797b1a6c65fa6b8",
      "boot_wait": "5s",
      "disk_size": 1,
      "headless": true,
      "shutdown_command": "poweroff",
      "ssh_password": "vagrant",
      "ssh_port": 22,
      "ssh_timeout": "10s",
      "ssh_username": "root",
      "type": "vmware-iso"
    },
    {
      "name": "alpine38",
      "output_directory": "output/alpine38",
      "iso_url": "https://sjc.edge.kernel.org/alpine/v3.8/releases/x86_64/alpine-virt-3.8.5-x86_64.iso",
      "iso_checksum": "sha256:9c1d8222c6af31f5e1e62dc25b5f4f922a27a6b3c7f8e136febd0c66dcdb51e3",
      "boot_wait": "5s",
      "disk_size": 1,
      "headless": true,
      "shutdown_command": "poweroff",
      "ssh_password": "vagrant",
      "ssh_port": 22,
      "ssh_timeout": "10s",
      "ssh_username": "root",
      "type": "vmware-iso"
    },
    {
      "name": "alpine39",
      "output_directory": "output/alpine39",
      "iso_url": "https://sjc.edge.kernel.org/alpine/v3.9/releases/x86_64/alpine-virt-3.9.6-x86_64.iso",
      "iso_checksum": "sha256:888d2245ec900351d3613d831838d1459ac29635b56bd528cd50fd643200d4cf",
      "boot_wait": "5s",
      "disk_size": 1,
      "headless": true,
      "shutdown_command": "poweroff",
      "ssh_password": "vagrant",
      "ssh_port": 22,
      "ssh_timeout": "10s",
      "ssh_username": "root",
      "type": "vmware-iso"
    },
    {
      "name": "alpine310",
      "output_directory": "output/alpine310",
      "iso_url": "https://sjc.edge.kernel.org/alpine/v3.10/releases/x86_64/alpine-virt-3.10.5-x86_64.iso",
      "iso_checksum": "sha256:dd3e01b9f7e0c00347cb9dd1be44673d20290d2388b316aec590faa1a5cdea9b",
      "boot_wait": "5s",
      "disk_size": 1,
      "headless": true,
      "shutdown_command": "poweroff",
      "ssh_password": "vagrant",
      "ssh_port": 22,
      "ssh_timeout": "10s",
      "ssh_username": "root",
      "type": "vmware-iso"
    },
    {
      "name": "alpine311",
      "output_directory": "output/alpine311",
      "iso_url": "https://sjc.edge.kernel.org/alpine/v3.11/releases/x86_64/alpine-virt-3.11.7-x86_64.iso",
      "iso_checksum": "sha256:05dff4d43ee5eacfe8fc4cd1cff68579f125f8c7430c02a7201cebe9672a6334",
      "boot_wait": "5s",
      "disk_size": 1,
      "headless": true,
      "shutdown_command": "poweroff",
      "ssh_password": "vagrant",
      "ssh_port": 22,
      "ssh_timeout": "10s",
      "ssh_username": "root",
      "type": "vmware-iso"
    },
    {
      "name": "alpine312",
      "output_directory": "output/alpine312",
      "iso_url": "https://sjc.edge.kernel.org/alpine/v3.12/releases/x86_64/alpine-virt-3.12.3-x86_64.iso",
      "iso_checksum": "sha256:fde694b984c737c303f68c1f6e178264185168561c9c8cdf080e3579e54fae96",
      "boot_wait": "5s",
      "disk_size": 1,
      "headless": true,
      "shutdown_command": "poweroff",
      "ssh_password": "vagrant",
      "ssh_port": 22,
      "ssh_timeout": "10s",
      "ssh_username": "root",
      "type": "vmware-iso"
    },
    {
      "name": "arch",
      "output_directory": "output/arch",
      "iso_url": "https://mirrors.edge.kernel.org/archlinux/iso/latest/archlinux-2021.01.01-x86_64.iso",
      "iso_checksum": "sha256:ae1b2c56a0a9a6d67a8ee9a7f0aef11eb556509bc6fae15fbd914689c290a45e",
      "boot_wait": "5s",
      "disk_size": 1,
      "headless": true,
      "shutdown_command": "poweroff",
      "ssh_password": "vagrant",
      "ssh_port": 22,
      "ssh_timeout": "10s",
      "ssh_username": "root",
      "type": "vmware-iso"
    },
    {
      "name": "centos6",
      "output_directory": "output/centos6",
      "iso_url": "https://vault.centos.org/6.10/isos/x86_64/CentOS-6.10-x86_64-minimal.iso",
      "iso_checksum": "sha256:7c0dee2a0494dabd84809b72ddb4b761f9ef92b78a506aef709b531c54d30770",
      "boot_wait": "5s",
      "disk_size": 1,
      "headless": true,
      "shutdown_command": "poweroff",
      "ssh_password": "vagrant",
      "ssh_port": 22,
      "ssh_timeout": "10s",
      "ssh_username": "root",
      "type": "vmware-iso"
    },
    {
      "name": "centos7",
      "output_directory": "output/centos7",
      "iso_url": "https://mirrors.edge.kernel.org/centos/7.9.2009/isos/x86_64/CentOS-7-x86_64-Minimal-2009.iso",
      "iso_checksum": "sha256:07b94e6b1a0b0260b94c83d6bb76b26bf7a310dc78d7a9c7432809fb9bc6194a",
      "boot_wait": "5s",
      "disk_size": 1,
      "headless": true,
      "shutdown_command": "poweroff",
      "ssh_password": "vagrant",
      "ssh_port": 22,
      "ssh_timeout": "10s",
      "ssh_username": "root",
      "type": "vmware-iso"
    },
    {
      "name": "centos8",
      "output_directory": "output/centos8",
      "iso_url": "https://mirrors.edge.kernel.org/centos/8.3.2011/isos/x86_64/CentOS-8.3.2011-x86_64-dvd1.iso",
      "iso_checksum": "sha256:aaf9d4b3071c16dbbda01dfe06085e5d0fdac76df323e3bbe87cce4318052247",
      "boot_wait": "5s",
      "disk_size": 1,
      "headless": true,
      "shutdown_command": "poweroff",
      "ssh_password": "vagrant",
      "ssh_port": 22,
      "ssh_timeout": "10s",
      "ssh_username": "root",
      "type": "vmware-iso"
    },
    {
      "name": "debian8",
      "output_directory": "output/debian8",
      "iso_url": "https://gensho.ftp.acc.umu.se/mirror/cdimage/archive/8.11.1/amd64/iso-cd/debian-8.11.1-amd64-netinst.iso",
      "iso_checksum": "sha256:ea444d6f8ac95fd51d2aedb8015c57410d1ad19b494cedec6914c17fda02733c",
      "boot_wait": "5s",
      "disk_size": 1,
      "headless": true,
      "shutdown_command": "poweroff",
      "ssh_password": "vagrant",
      "ssh_port": 22,
      "ssh_timeout": "10s",
      "ssh_username": "root",
      "type": "vmware-iso"
    },
    {
      "name": "debian9",
      "output_directory": "output/debian9",
      "iso_url": "https://ftp.acc.umu.se/mirror/cdimage/archive/9.13.0/amd64/iso-cd/debian-9.13.0-amd64-netinst.iso",
      "iso_checksum": "sha256:71c7e9eb292acc880f84605b1ca2b997f25737fe0a43fc9586f61d35cd2eb43b",
      "boot_wait": "5s",
      "disk_size": 1,
      "headless": true,
      "shutdown_command": "poweroff",
      "ssh_password": "vagrant",
      "ssh_port": 22,
      "ssh_timeout": "10s",
      "ssh_username": "root",
      "type": "vmware-iso"
    },
    {
      "name": "debian9-x32",
      "output_directory": "output/debian9-x32",
      "iso_url": "https://ftp.acc.umu.se/mirror/cdimage/archive/9.13.0/i386/iso-cd/debian-9.13.0-i386-netinst.iso",
      "iso_checksum": "sha256:27de998af87007bf5daa3030d3863d3ef801b948c29f5bbce232be4f928eedba",
      "boot_wait": "5s",
      "disk_size": 1,
      "headless": true,
      "shutdown_command": "poweroff",
      "ssh_password": "vagrant",
      "ssh_port": 22,
      "ssh_timeout": "10s",
      "ssh_username": "root",
      "type": "vmware-iso"
    },
    {
      "name": "debian10",
      "output_directory": "output/debian10",
      "iso_url": "https://gensho.ftp.acc.umu.se/debian-cd/current/amd64/iso-cd/debian-10.7.0-amd64-netinst.iso",
      "iso_checksum": "sha256:b317d87b0a3d5b568f48a92dcabfc4bc51fe58d9f67ca13b013f1b8329d1306d",
      "boot_wait": "5s",
      "disk_size": 1,
      "headless": true,
      "shutdown_command": "poweroff",
      "ssh_password": "vagrant",
      "ssh_port": 22,
      "ssh_timeout": "10s",
      "ssh_username": "root",
      "type": "vmware-iso"
    },
    {
      "name": "devuan1",
      "output_directory": "output/devuan1",
      "iso_url": "https://mirror.leaseweb.com/devuan/devuan_jessie/installer-iso/devuan_jessie_1.0.0_amd64_NETINST.iso",
      "iso_checksum": "sha256:70c6abe544ec59b0d0882c666ca0377be1b6c218655dac1f61b2c7e88c9b3d9f",
      "boot_wait": "5s",
      "disk_size": 1,
      "headless": true,
      "shutdown_command": "poweroff",
      "ssh_password": "vagrant",
      "ssh_port": 22,
      "ssh_timeout": "10s",
      "ssh_username": "root",
      "type": "vmware-iso"
    },
    {
      "name": "devuan2",
      "output_directory": "output/devuan2",
      "iso_url": "https://mirror.leaseweb.com/devuan/devuan_ascii/installer-iso/devuan_ascii_2.1_amd64_netinst.iso",
      "iso_checksum": "sha256:9aa6de460fb944ddfec8c79306974a522be166e4d296e9673f083f9e1cc6c56c",
      "boot_wait": "5s",
      "disk_size": 1,
      "headless": true,
      "shutdown_command": "poweroff",
      "ssh_password": "vagrant",
      "ssh_port": 22,
      "ssh_timeout": "10s",
      "ssh_username": "root",
      "type": "vmware-iso"
    },
    {
      "name": "devuan3",
      "output_directory": "output/devuan3",
      "iso_url": "https://mirror.leaseweb.com/devuan/devuan_beowulf/installer-iso/devuan_beowulf_3.0.0_amd64-netinstall.iso",
      "iso_checksum": "sha256:5844e45dc6421c25dfc9fb25df9d57af8fadf12a97a2a4e0ae1931c4c3217523",
      "boot_wait": "5s",
      "disk_size": 1,
      "headless": true,
      "shutdown_command": "poweroff",
      "ssh_password": "vagrant",
      "ssh_port": 22,
      "ssh_timeout": "10s",
      "ssh_username": "root",
      "type": "vmware-iso"
    },
    {
      "name": "dragonflybsd5",
      "output_directory": "output/dragonflybsd5",
      "iso_url": "https://mirror-master.dragonflybsd.org/iso-images/dfly-x86_64-5.8.3_REL.iso",
      "iso_checksum": "sha256:8c169e787822ab743e0ee7ddb97c2f4181316ebcd7f7a3e82a085c30f3ea29b5",
      "boot_wait": "5s",
      "disk_size": 1,
      "headless": true,
      "shutdown_command": "poweroff",
      "ssh_password": "vagrant",
      "ssh_port": 22,
      "ssh_timeout": "10s",
      "ssh_username": "root",
      "type": "vmware-iso"
    },
    {
      "name": "dragonflybsd5-hyperv",
      "output_directory": "output/dragonflybsd5-hyperv",
      "iso_url": "https://archive.org/download/dfly-x86_64-5.6.3_REL/dfly-x86_64-5.6.3_REL.iso",
      "iso_checksum": "sha256:7f95358f8c359ebedf433cd0604096fa1bc1f86b6188cbd9550b146f9f5478b8",
      "boot_wait": "5s",
      "disk_size": 1,
      "headless": true,
      "shutdown_command": "poweroff",
      "ssh_password": "vagrant",
      "ssh_port": 22,
      "ssh_timeout": "10s",
      "ssh_username": "root",
      "type": "vmware-iso"
    },
    {
      "name": "fedora25",
      "output_directory": "output/fedora25",
      "iso_url": "https://archives.fedoraproject.org/pub/archive/fedora/linux/releases/25/Server/x86_64/iso/Fedora-Server-netinst-x86_64-25-1.3.iso",
      "iso_checksum": "sha256:86bc3694f4938382753d1e9536f2140a6c9c1978207766340c679a89509073c7",
      "boot_wait": "5s",
      "disk_size": 1,
      "headless": true,
      "shutdown_command": "poweroff",
      "ssh_password": "vagrant",
      "ssh_port": 22,
      "ssh_timeout": "10s",
      "ssh_username": "root",
      "type": "vmware-iso"
    },
    {
      "name": "fedora26",
      "output_directory": "output/fedora26",
      "iso_url": "https://archives.fedoraproject.org/pub/archive/fedora/linux/releases/26/Server/x86_64/iso/Fedora-Server-netinst-x86_64-26-1.5.iso",
      "iso_checksum": "sha256:e260921ef5c7bd5ee2a7b2f2f1156af6483014c73984e4cf37f2b6690e0155e5",
      "boot_wait": "5s",
      "disk_size": 1,
      "headless": true,
      "shutdown_command": "poweroff",
      "ssh_password": "vagrant",
      "ssh_port": 22,
      "ssh_timeout": "10s",
      "ssh_username": "root",
      "type": "vmware-iso"
    },
    {
      "name": "fedora27",
      "output_directory": "output/fedora27",
      "iso_url": "https://archives.fedoraproject.org/pub/archive/fedora/linux/releases/27/Server/x86_64/iso/Fedora-Server-netinst-x86_64-27-1.6.iso",
      "iso_checksum": "sha256:2b93836c38833b26891345388ff5ddea60529b27a616b4539d432a3520d1c90b",
      "boot_wait": "5s",
      "disk_size": 1,
      "headless": true,
      "shutdown_command": "poweroff",
      "ssh_password": "vagrant",
      "ssh_port": 22,
      "ssh_timeout": "10s",
      "ssh_username": "root",
      "type": "vmware-iso"
    },
    {
      "name": "fedora28",
      "output_directory": "output/fedora28",
      "iso_url": "https://archives.fedoraproject.org/pub/archive/fedora/linux/releases/28/Server/x86_64/iso/Fedora-Server-netinst-x86_64-28-1.1.iso",
      "iso_checksum": "sha256:ea1efdc692356b3346326f82e2f468903e8da59324fdee8b10eac4fea83f23fe",
      "boot_wait": "5s",
      "disk_size": 1,
      "headless": true,
      "shutdown_command": "poweroff",
      "ssh_password": "vagrant",
      "ssh_port": 22,
      "ssh_timeout": "10s",
      "ssh_username": "root",
      "type": "vmware-iso"
    },
    {
      "name": "fedora29",
      "output_directory": "output/fedora29",
      "iso_url": "https://archives.fedoraproject.org/pub/archive/fedora/linux/releases/29/Server/x86_64/iso/Fedora-Server-netinst-x86_64-29-1.2.iso",
      "iso_checksum": "sha256:aa7fb0e6e5b71774ebdaab0dae76bdd9246a5bc7aedc28b7f1103aaaf9750654",
      "boot_wait": "5s",
      "disk_size": 1,
      "headless": true,
      "shutdown_command": "poweroff",
      "ssh_password": "vagrant",
      "ssh_port": 22,
      "ssh_timeout": "10s",
      "ssh_username": "root",
      "type": "vmware-iso"
    },
    {
      "name": "fedora30",
      "output_directory": "output/fedora30",
      "iso_url": "https://archives.fedoraproject.org/pub/archive/fedora/linux/releases/30/Server/x86_64/iso/Fedora-Server-netinst-x86_64-30-1.2.iso",
      "iso_checksum": "sha256:5e4eac4566d8c572bfb3bcf54b7d6c82006ec3c6c882a2c9235c6d3494d7b100",
      "boot_wait": "5s",
      "disk_size": 1,
      "headless": true,
      "shutdown_command": "poweroff",
      "ssh_password": "vagrant",
      "ssh_port": 22,
      "ssh_timeout": "10s",
      "ssh_username": "root",
      "type": "vmware-iso"
    },
    {
      "name": "fedora31",
      "output_directory": "output/fedora31",
      "iso_url": "https://archives.fedoraproject.org/pub/archive/fedora/linux/releases/31/Server/x86_64/iso/Fedora-Server-netinst-x86_64-31-1.9.iso",
      "iso_checksum": "sha256:5be8debd3e8fb4e86b9fbf67c7eb66ea598d2b7ad0c7ba8d505ce88067b43444",
      "boot_wait": "5s",
      "disk_size": 1,
      "headless": true,
      "shutdown_command": "poweroff",
      "ssh_password": "vagrant",
      "ssh_port": 22,
      "ssh_timeout": "10s",
      "ssh_username": "root",
      "type": "vmware-iso"
    },
    {
      "name": "fedora32",
      "output_directory": "output/fedora32",
      "iso_url": "https://dl.fedoraproject.org/pub/fedora/linux/releases/32/Server/x86_64/iso/Fedora-Server-netinst-x86_64-32-1.6.iso",
      "iso_checksum": "sha256:7f4afd2a26c718f9f15e4bbfd9c2e8849f81036d2a82a4e81fa4a313a833da9c",
      "boot_wait": "5s",
      "disk_size": 1,
      "headless": true,
      "shutdown_command": "poweroff",
      "ssh_password": "vagrant",
      "ssh_port": 22,
      "ssh_timeout": "10s",
      "ssh_username": "root",
      "type": "vmware-iso"
    },
    {
      "name": "fedora33",
      "output_directory": "output/fedora33",
      "iso_url": "https://dl.fedoraproject.org/pub/fedora/linux/releases/33/Server/x86_64/iso/Fedora-Server-netinst-x86_64-33-1.2.iso",
      "iso_checksum": "sha256:1f1f018e78f0cc23d08db0c85952344ea5c200e67b672da5b07507c066a52ccf",
      "boot_wait": "5s",
      "disk_size": 1,
      "headless": true,
      "shutdown_command": "poweroff",
      "ssh_password": "vagrant",
      "ssh_port": 22,
      "ssh_timeout": "10s",
      "ssh_username": "root",
      "type": "vmware-iso"
    },
    {
      "name": "freebsd11",
      "output_directory": "output/freebsd11",
      "iso_url": "https://download.freebsd.org/ftp/releases/ISO-IMAGES/11.4/FreeBSD-11.4-RELEASE-amd64-disc1.iso",
      "iso_checksum": "sha256:d76c1ded99b2c1005b1ff94cc0c811fbcd8a2d04196432009ab5f203c2146914",
      "boot_wait": "5s",
      "disk_size": 1,
      "headless": true,
      "shutdown_command": "poweroff",
      "ssh_password": "vagrant",
      "ssh_port": 22,
      "ssh_timeout": "10s",
      "ssh_username": "root",
      "type": "vmware-iso"
    },
    {
      "name": "freebsd12",
      "output_directory": "output/freebsd12",
      "iso_url": "https://download.freebsd.org/ftp/releases/ISO-IMAGES/12.2/FreeBSD-12.2-RELEASE-amd64-disc1.iso",
      "iso_checksum": "sha256:289522e2f4e1260859505adab6d7b54ab83d19aeb147388ff7e28019984da5dc",
      "boot_wait": "5s",
      "disk_size": 1,
      "headless": true,
      "shutdown_command": "poweroff",
      "ssh_password": "vagrant",
      "ssh_port": 22,
      "ssh_timeout": "10s",
      "ssh_username": "root",
      "type": "vmware-iso"
    },
    {
      "name": "gentoo",
      "output_directory": "output/gentoo",
      "iso_url": "https://mirrors.kernel.org/gentoo/releases/amd64/autobuilds/current-install-amd64-minimal/install-amd64-minimal-20210110T214504Z.iso",
      "iso_checksum": "sha256:63e804c09c211aafa3f5d406690a3fd8895eadacb5d9ba6fa7d71bfaf5380ed1",
      "boot_wait": "5s",
      "disk_size": 1,
      "headless": true,
      "shutdown_command": "poweroff",
      "ssh_password": "vagrant",
      "ssh_port": 22,
      "ssh_timeout": "10s",
      "ssh_username": "root",
      "type": "vmware-iso"
    },
    {
      "name": "hardenedbsd11",
      "output_directory": "output/hardenedbsd11",
      "iso_url": "https://dk-01.installer.hardenedbsd.org/pub/HardenedBSD/releases/amd64/amd64/ISO-IMAGES/hardenedbsd-11-stable-20190205-1/HardenedBSD-11-STABLE-v1100056.13-amd64-disc1.iso",
      "iso_checksum": "sha256:8b2c90dc41ec68b561028af885eecb66bfd36223970d1c594923d1d54bf83467",
      "boot_wait": "5s",
      "disk_size": 1,
      "headless": true,
      "shutdown_command": "poweroff",
      "ssh_password": "vagrant",
      "ssh_port": 22,
      "ssh_timeout": "10s",
      "ssh_username": "root",
      "type": "vmware-iso"
    },
    {
      "name": "hardenedbsd12",
      "output_directory": "output/hardenedbsd12",
      "iso_url": "https://dk-01.installer.hardenedbsd.org/pub/HardenedBSD/releases/amd64/amd64/ISO-IMAGES/hardenedbsd-12-stable-20190807-1/HardenedBSD-12-STABLE-v1200059.3-amd64-disc1.iso",
      "iso_checksum": "sha256:029225eaf92ba8e7ed7a7395f45492d09bc9a949488ecb9a5ca54df7c9f89661",
      "boot_wait": "5s",
      "disk_size": 1,
      "headless": true,
      "shutdown_command": "poweroff",
      "ssh_password": "vagrant",
      "ssh_port": 22,
      "ssh_timeout": "10s",
      "ssh_username": "root",
      "type": "vmware-iso"
    },
    {
      "name": "netbsd8",
      "output_directory": "output/netbsd8",
      "iso_url": "https://ftp.netbsd.org/pub/NetBSD/iso/8.2/NetBSD-8.2-amd64.iso",
      "iso_checksum": "sha256:55d03c51d5b94cf7f03a29c1ee7e9f49d6b0ec4c2e1b1a2523c03956b70a1841",
      "boot_wait": "5s",
      "disk_size": 1,
      "headless": true,
      "shutdown_command": "poweroff",
      "ssh_password": "vagrant",
      "ssh_port": 22,
      "ssh_timeout": "10s",
      "ssh_username": "root",
      "type": "vmware-iso"
    },
    {
      "name": "netbsd9",
      "output_directory": "output/netbsd9",
      "iso_url": "https://ftp.netbsd.org/pub/NetBSD/iso/9.1/NetBSD-9.1-amd64.iso",
      "iso_checksum": "sha256:de37b3071fc02d308c10df39794f1f272883243b0948223d410fdaf1bfefbd39",
      "boot_wait": "5s",
      "disk_size": 1,
      "headless": true,
      "shutdown_command": "poweroff",
      "ssh_password": "vagrant",
      "ssh_port": 22,
      "ssh_timeout": "10s",
      "ssh_username": "root",
      "type": "vmware-iso"
    },
    {
      "name": "openbsd6",
      "output_directory": "output/openbsd6",
      "iso_url": "https://ftp.openbsd.org/pub/OpenBSD/6.8/amd64/cd68.iso",
      "iso_checksum": "sha256:05fb374fa25461d2315349214228ee671d8bae45f16da994283a8cf9c848451c",
      "boot_wait": "5s",
      "disk_size": 1,
      "headless": true,
      "shutdown_command": "poweroff",
      "ssh_password": "vagrant",
      "ssh_port": 22,
      "ssh_timeout": "10s",
      "ssh_username": "root",
      "type": "vmware-iso"
    },
    {
      "name": "opensuse15",
      "output_directory": "output/opensuse15",
      "iso_url": "https://mirrors.edge.kernel.org/opensuse/distribution/leap/15.2/iso/openSUSE-Leap-15.2-NET-x86_64.iso",
      "iso_checksum": "sha256:02a77812443dd3e47c36611c8837bf8d1659aea6b4d16c9db6841c564d59b7af",
      "boot_wait": "5s",
      "disk_size": 1,
      "headless": true,
      "shutdown_command": "poweroff",
      "ssh_password": "vagrant",
      "ssh_port": 22,
      "ssh_timeout": "10s",
      "ssh_username": "root",
      "type": "vmware-iso"
    },
    {
      "name": "opensuse42",
      "output_directory": "output/opensuse42",
      "iso_url": "https://ftp5.gwdg.de/pub/opensuse/discontinued/distribution/leap/42.3/iso/openSUSE-Leap-42.3-NET-x86_64.iso",
      "iso_checksum": "sha256:d1a17116cf33a5582b83ef479d7b151b33938e60f07eebc544abf162e2aa5c12",
      "boot_wait": "5s",
      "disk_size": 1,
      "headless": true,
      "shutdown_command": "poweroff",
      "ssh_password": "vagrant",
      "ssh_port": 22,
      "ssh_timeout": "10s",
      "ssh_username": "root",
      "type": "vmware-iso"
    },
    {
      "name": "oracle7",
      "output_directory": "output/oracle7",
      "iso_url": "https://mirrors.kernel.org/oracle/OL7/u9/x86_64/OracleLinux-R7-U9-Server-x86_64-dvd.iso",
      "iso_checksum": "sha256:dc2782bfd92b4c060cf8006fbc6e18036c27f599eebf3584a1a2ac54f008bf2f",
      "boot_wait": "5s",
      "disk_size": 1,
      "headless": true,
      "shutdown_command": "poweroff",
      "ssh_password": "vagrant",
      "ssh_port": 22,
      "ssh_timeout": "10s",
      "ssh_username": "root",
      "type": "vmware-iso"
    },
    {
      "name": "oracle8",
      "output_directory": "output/oracle8",
      "iso_url": "https://mirrors.kernel.org/oracle/OL8/u3/x86_64/OracleLinux-R8-U3-x86_64-dvd.iso",
      "iso_checksum": "sha256:771e383adfd5406d1a360ff24822011a88cbb45b6019e2f1095758c46a406aaa",
      "boot_wait": "5s",
      "disk_size": 1,
      "headless": true,
      "shutdown_command": "poweroff",
      "ssh_password": "vagrant",
      "ssh_port": 22,
      "ssh_timeout": "10s",
      "ssh_username": "root",
      "type": "vmware-iso"
    },
    {
      "name": "rhel6",
      "output_directory": "output/rhel6",
      "iso_url": "https://archive.org/download/rhel-server-6.10-x86_64-dvd/rhel-server-6.10-x86_64-dvd.iso",
      "iso_checksum": "sha256:1e15f9202d2cdd4b2bdf9d6503a8543347f0cb8cc06ba9a0dfd2df4fdef5c727",
      "boot_wait": "5s",
      "disk_size": 1,
      "headless": true,
      "shutdown_command": "poweroff",
      "ssh_password": "vagrant",
      "ssh_port": 22,
      "ssh_timeout": "10s",
      "ssh_username": "root",
      "type": "vmware-iso"
    },
    {
      "name": "rhel7",
      "output_directory": "output/rhel7",
      "iso_url": "https://archive.org/download/rhel-server-7.9-x86_64-dvd/rhel-server-7.9-x86_64-dvd.iso",
      "iso_checksum": "sha256:19d653ce2f04f202e79773a0cbeda82070e7527557e814ebbce658773fbe8191",
      "boot_wait": "5s",
      "disk_size": 1,
      "headless": true,
      "shutdown_command": "poweroff",
      "ssh_password": "vagrant",
      "ssh_port": 22,
      "ssh_timeout": "10s",
      "ssh_username": "root",
      "type": "vmware-iso"
    },
    {
      "name": "rhel8",
      "output_directory": "output/rhel8",
      "iso_url": "https://archive.org/download/rhel-8.3-x86_64-dvd/rhel-8.3-x86_64-dvd.iso",
      "iso_checksum": "sha256:30fd8dff2d29a384bd97886fa826fa5be872213c81e853eae3f9d9674f720ad0",
      "boot_wait": "5s",
      "disk_size": 1,
      "headless": true,
      "shutdown_command": "poweroff",
      "ssh_password": "vagrant",
      "ssh_port": 22,
      "ssh_timeout": "10s",
      "ssh_username": "root",
      "type": "vmware-iso"
    },
    {
      "name": "ubuntu1604",
      "output_directory": "output/ubuntu1604",
      "iso_url": "https://mirrors.kernel.org/ubuntu-releases/16.04.7/ubuntu-16.04.7-server-amd64.iso",
      "iso_checksum": "sha256:b23488689e16cad7a269eb2d3a3bf725d3457ee6b0868e00c8762d3816e25848",
      "boot_wait": "5s",
      "disk_size": 1,
      "headless": true,
      "shutdown_command": "poweroff",
      "ssh_password": "vagrant",
      "ssh_port": 22,
      "ssh_timeout": "10s",
      "ssh_username": "root",
      "type": "vmware-iso"
    },
    {
      "name": "ubuntu1610",
      "output_directory": "output/ubuntu1610",
      "iso_url": "http://old-releases.ubuntu.com/releases/16.10/ubuntu-16.10-server-amd64.iso",
      "iso_checksum": "sha256:72b0d421da77f1e0c549b4efe6fc6c184e9909d6792f0d1e59b56d63e9705659",
      "boot_wait": "5s",
      "disk_size": 1,
      "headless": true,
      "shutdown_command": "poweroff",
      "ssh_password": "vagrant",
      "ssh_port": 22,
      "ssh_timeout": "10s",
      "ssh_username": "root",
      "type": "vmware-iso"
    },
    {
      "name": "ubuntu1704",
      "output_directory": "output/ubuntu1704",
      "iso_url": "http://old-releases.ubuntu.com/releases/17.04/ubuntu-17.04-server-amd64.iso",
      "iso_checksum": "sha256:ca5d9a8438e2434b9a3ac2be67b5c5fa2c1f8e3e40b954519462935195464034",
      "boot_wait": "5s",
      "disk_size": 1,
      "headless": true,
      "shutdown_command": "poweroff",
      "ssh_password": "vagrant",
      "ssh_port": 22,
      "ssh_timeout": "10s",
      "ssh_username": "root",
      "type": "vmware-iso"
    },
    {
      "name": "ubuntu1710",
      "output_directory": "output/ubuntu1710",
      "iso_url": "http://old-releases.ubuntu.com/releases/17.10/ubuntu-17.10.1-server-amd64.iso",
      "iso_checksum": "sha256:8ff73f1b622276758475c3bd5190b382774626de5a82c50930519381f6c3a3f8",
      "boot_wait": "5s",
      "disk_size": 1,
      "headless": true,
      "shutdown_command": "poweroff",
      "ssh_password": "vagrant",
      "ssh_port": 22,
      "ssh_timeout": "10s",
      "ssh_username": "root",
      "type": "vmware-iso"
    },
    {
      "name": "ubuntu1804",
      "output_directory": "output/ubuntu1804",
      "iso_url": "http://cdimage.ubuntu.com/ubuntu/releases/18.04.5/release/ubuntu-18.04.5-server-amd64.iso",
      "iso_checksum": "sha256:8c5fc24894394035402f66f3824beb7234b757dd2b5531379cb310cedfdf0996",
      "boot_wait": "5s",
      "disk_size": 1,
      "headless": true,
      "shutdown_command": "poweroff",
      "ssh_password": "vagrant",
      "ssh_port": 22,
      "ssh_timeout": "10s",
      "ssh_username": "root",
      "type": "vmware-iso"
    },
    {
      "name": "ubuntu1810",
      "output_directory": "output/ubuntu1810",
      "iso_url": "http://old-releases.ubuntu.com/releases/18.10/ubuntu-18.10-server-amd64.iso",
      "iso_checksum": "sha256:cf9250781dadd919f23c9d9612212cad653e35fccc2fbcf6853f67ad09e067ba",
      "boot_wait": "5s",
      "disk_size": 1,
      "headless": true,
      "shutdown_command": "poweroff",
      "ssh_password": "vagrant",
      "ssh_port": 22,
      "ssh_timeout": "10s",
      "ssh_username": "root",
      "type": "vmware-iso"
    },
    {
      "name": "ubuntu1904",
      "output_directory": "output/ubuntu1904",
      "iso_url": "http://old-releases.ubuntu.com/releases/19.04/ubuntu-19.04-server-amd64.iso",
      "iso_checksum": "sha256:7e8a0d07522f591dfee9bc9fcd7c05466763161e6cb0117906655bce1750b2fa",
      "boot_wait": "5s",
      "disk_size": 1,
      "headless": true,
      "shutdown_command": "poweroff",
      "ssh_password": "vagrant",
      "ssh_port": 22,
      "ssh_timeout": "10s",
      "ssh_username": "root",
      "type": "vmware-iso"
    },
    {
      "name": "ubuntu1910",
      "output_directory": "output/ubuntu1910",
      "iso_url": "https://archive.org/download/ubuntu-19.10-server-amd64/ubuntu-19.10-server-amd64.iso",
      "iso_checksum": "sha256:921fd8b271c04aa86a321cc35b40e677f9b85f7903bf2204efb2389b0f0a64c1",
      "boot_wait": "5s",
      "disk_size": 1,
      "headless": true,
      "shutdown_command": "poweroff",
      "ssh_password": "vagrant",
      "ssh_port": 22,
      "ssh_timeout": "10s",
      "ssh_username": "root",
      "type": "vmware-iso"
    },
    {
      "name": "ubuntu2004",
      "output_directory": "output/ubuntu2004",
      "iso_url": "http://cdimage.ubuntu.com/ubuntu-legacy-server/releases/20.04.1/release/ubuntu-20.04.1-legacy-server-amd64.iso",
      "iso_checksum": "sha256:f11bda2f2caed8f420802b59f382c25160b114ccc665dbac9c5046e7fceaced2",
      "boot_wait": "5s",
      "disk_size": 1,
      "headless": true,
      "shutdown_command": "poweroff",
      "ssh_password": "vagrant",
      "ssh_port": 22,
      "ssh_timeout": "10s",
      "ssh_username": "root",
      "type": "vmware-iso"
    },
    {
      "name": "ubuntu2010",
      "output_directory": "output/ubuntu2010",
      "iso_url": "https://mirrors.kernel.org/ubuntu-releases/20.10/ubuntu-20.10-live-server-amd64.iso",
      "iso_checksum": "sha256:defdc1ad3af7b661fe2b4ee861fb6fdb5f52039389ef56da6efc05e6adfe3d45",
      "boot_wait": "5s",
      "disk_size": 1,
      "headless": true,
      "shutdown_command": "poweroff",
      "ssh_password": "vagrant",
      "ssh_port": 22,
      "ssh_timeout": "10s",
      "ssh_username": "root",
      "type": "vmware-iso"
    },
    {
      "name": "virtualbox-5-1-14",
      "output_directory": "output/virtualbox-5-1-14",
      "iso_url": "https://download.virtualbox.org/virtualbox/5.1.14/VBoxGuestAdditions_5.1.14.iso",
      "iso_checksum": "sha256:1b206b76050dccd3ed979307230f9ddea79551e1c0aba93faee77416733cdc8a",
      "boot_wait": "5s",
      "disk_size": 1,
      "headless": true,
      "shutdown_command": "poweroff",
      "ssh_password": "vagrant",
      "ssh_port": 22,
      "ssh_timeout": "10s",
      "ssh_username": "root",
      "type": "vmware-iso"
    },
    {
      "name": "virtualbox-5-1-38",
      "output_directory": "output/virtualbox-5-1-38",
      "iso_url": "https://download.virtualbox.org/virtualbox/5.1.38/VBoxGuestAdditions_5.1.38.iso",
      "iso_checksum": "sha256:0e7ee2c78ebf7cd0d3a933d51148bef04a64f64fb27ccf70d59cddf9ca1e517a",
      "boot_wait": "5s",
      "disk_size": 1,
      "headless": true,
      "shutdown_command": "poweroff",
      "ssh_password": "vagrant",
      "ssh_port": 22,
      "ssh_timeout": "10s",
      "ssh_username": "root",
      "type": "vmware-iso"
    },
    {
      "name": "virtualbox-5-2-44",
      "output_directory": "output/virtualbox-5-2-44",
      "iso_url": "https://download.virtualbox.org/virtualbox/5.2.44/VBoxGuestAdditions_5.2.44.iso",
      "iso_checksum": "sha256:9883ee443a309f4ffa1d5dee2833f9e35ced598686c36d159f410e5edbac1ca4",
      "boot_wait": "5s",
      "disk_size": 1,
      "headless": true,
      "shutdown_command": "poweroff",
      "ssh_password": "vagrant",
      "ssh_port": 22,
      "ssh_timeout": "10s",
      "ssh_username": "root",
      "type": "vmware-iso"
    }
  ]
}
